csv2numbers/__init__.py
csv2numbers/__main__.py
csv2numbers/_csv2numbers.py
csv2numbers-1.1.1.dist-info/LICENSE.rst
csv2numbers-1.1.1.dist-info/METADATA
csv2numbers-1.1.1.dist-info/WHEEL
csv2numbers-1.1.1.dist-info/entry_points.txt
csv2numbers-1.1.1.dist-info/RECORD
