Metadata-Version: 2.1
Name: csv2numbers
Version: 1.1.1
Summary: Automator scripts
Home-page: https://github.com/masaccio/csv2numbers
Author: Jon Connell
Author-email: python@figsandfudge.com
Requires-Python: >=3.9,<3.13
Classifier: Programming Language :: Python :: 3
Classifier: Programming Language :: Python :: 3.9
Classifier: Programming Language :: Python :: 3.10
Classifier: Programming Language :: Python :: 3.11
Requires-Dist: numbers-parser (>=4.4.6,<5.0.0)
Requires-Dist: pandas (>=2.1.1,<3.0.0)
Project-URL: Repository, https://github.com/masaccio/csv2numbers
